LICENSE.txt
README.md
setup.cfg
setup.py
ADbase/ADReverse.py
ADbase/ADbase.py
ADbase.egg-info/PKG-INFO
ADbase.egg-info/SOURCES.txt
ADbase.egg-info/dependency_links.txt
ADbase.egg-info/requires.txt
ADbase.egg-info/top_level.txt
test/test_ADbase.py