Metadata-Version: 2.1
Name: ADbase
Version: 0.1.7
Summary: Automatic differentiation library
Home-page: https://github.com/cs107-byteme/cs107-FinalProject
Author: CS107 Group 28: ByteMe
Author-email: gcpasco@college.harvard.edu
License: MIT
Download-URL: https://github.com/cs107-byteme/cs107-FinalProject/archive/refs/tags/alpha.tar.gz
Keywords: AUTOMATIC DIFFERENTIATION
Platform: UNKNOWN
Classifier: Development Status :: 3 - Alpha
Classifier: Intended Audience :: Developers
Classifier: Topic :: Software Development :: Build Tools
Classifier: License :: OSI Approved :: MIT License
Classifier: Programming Language :: Python :: 3
Classifier: Programming Language :: Python :: 3.4
Classifier: Programming Language :: Python :: 3.5
Classifier: Programming Language :: Python :: 3.6
License-File: LICENSE.txt
